model_service/__init__.py
model_service/app.py
model_service/client.py
model_service/command.py
model_service/common.py
model_service/error_code.py
model_service/frozen_graph_model_service.py
model_service/grpc_predict_v2_pb2.py
model_service/grpc_predict_v2_pb2_grpc.py
model_service/grpc_server.py
model_service/log.py
model_service/mnist_service.py
model_service/model_service.py
model_service/settings.py
model_service/tfserving_model_service.py
model_service/tfserving_vision_service.py
model_service/model_def/__init__.py
model_service/model_def/model_def.py
taichu_model_server-1.0.7.dist-info/METADATA
taichu_model_server-1.0.7.dist-info/WHEEL
taichu_model_server-1.0.7.dist-info/entry_points.txt
taichu_model_server-1.0.7.dist-info/top_level.txt
taichu_model_server-1.0.7.dist-info/RECORD
