Metadata-Version: 2.1
Name: taichu-model-server
Version: 1.0.7
Summary: taichu serve is a tool for serving deep learning inference
Home-page: 
Author: taichu platform team
Keywords: Serving Deep Learning Inference AI
Requires-Python: >=3.6.0
Requires-Dist: grpcio
Requires-Dist: grpc-tools
Requires-Dist: protobuf
Requires-Dist: Flask
Requires-Dist: gunicorn
Requires-Dist: Jinja2
Requires-Dist: Pillow
